pipreqs/__init__.py
pipreqs/mapping
pipreqs/pipreqs.py
pipreqs/stdlib
pipreqs_test-19.3.28.dist-info/AUTHORS.rst
pipreqs_test-19.3.28.dist-info/LICENSE
pipreqs_test-19.3.28.dist-info/METADATA
pipreqs_test-19.3.28.dist-info/WHEEL
pipreqs_test-19.3.28.dist-info/entry_points.txt
pipreqs_test-19.3.28.dist-info/top_level.txt
pipreqs_test-19.3.28.dist-info/RECORD
