Metadata-Version: 2.1
Name: pipreqs-test
Version: 19.3.28
Summary: Pip requirements.txt generator based on imports in project
Home-page: https://github.com/bndr/pipreqs
Author: Vadim Kravcenko
Author-email: vadim.kravcenko@gmail.com
License: Apache License
Keywords: pip requirements imports
Classifier: Development Status :: 4 - Beta
Classifier: Intended Audience :: Developers
Classifier: License :: OSI Approved :: Apache Software License
Classifier: Natural Language :: English
Classifier: Programming Language :: Python :: 3
Classifier: Programming Language :: Python :: 3.7
Classifier: Programming Language :: Python :: 3.8
Classifier: Programming Language :: Python :: 3.9
Classifier: Programming Language :: Python :: 3.10
Classifier: Programming Language :: Python :: 3.11
Requires-Python: >=3.7
License-File: LICENSE
License-File: AUTHORS.rst
Requires-Dist: docopt
Requires-Dist: yarg
